time_to_critical/__init__.py
time_to_critical/cli.py
time_to_critical/forecast.py
time_to_critical/plotting.py
time_to_critical/timeseries.py
time_to_critical/trend.py
time_to_critical-1.1.1.dist-info/licenses/LICENSE
time_to_critical-1.1.1.dist-info/METADATA
time_to_critical-1.1.1.dist-info/WHEEL
time_to_critical-1.1.1.dist-info/entry_points.txt
time_to_critical-1.1.1.dist-info/top_level.txt
time_to_critical-1.1.1.dist-info/RECORD
