Metadata-Version: 2.4
Name: time-to-critical
Version: 1.1.1
Summary: A Python CLI application for time series forecasting using FFT with automatic trend detection
Author-email: Octavio Deliberato Neto <octavio.deliberato@aggxtream.com>
License: MIT License
Project-URL: Homepage, https://github.com/yourusername/pytimetc
Project-URL: Repository, https://github.com/yourusername/pytimetc
Project-URL: Issues, https://github.com/yourusername/pytimetc/issues
Keywords: time-series,forecasting,fft,data-analysis,cli
Classifier: Development Status :: 4 - Beta
Classifier: Intended Audience :: Developers
Classifier: Intended Audience :: Science/Research
Classifier: License :: OSI Approved :: MIT License
Classifier: Programming Language :: Python :: 3
Classifier: Programming Language :: Python :: 3.9
Classifier: Programming Language :: Python :: 3.10
Classifier: Programming Language :: Python :: 3.11
Classifier: Programming Language :: Python :: 3.12
Classifier: Topic :: Scientific/Engineering
Classifier: Topic :: Software Development :: Libraries :: Python Modules
Requires-Python: >=3.9
License-File: LICENSE
Requires-Dist: numpy>=1.24.0
Requires-Dist: pandas>=2.0.0
Requires-Dist: matplotlib>=3.7.0
Requires-Dist: pyarrow>=12.0.0
Requires-Dist: python-dateutil>=2.8.0
Provides-Extra: dev
Requires-Dist: pytest>=7.4.0; extra == "dev"
Requires-Dist: pytest-cov>=4.1.0; extra == "dev"
Requires-Dist: pytest-benchmark>=4.0.0; extra == "dev"
Requires-Dist: ruff>=0.1.0; extra == "dev"
Requires-Dist: black>=23.0.0; extra == "dev"
Dynamic: license-file
